{
    "emxarms:1045x103": 34.67,
    "emxarms:1045x103belt": 34.67,
    "classicr:416barrett": 28.39,
    "tacz:50bmg": 30.57,
    "tacz:338": 18.09,
    "emxarms:339x57": 18.47,
    "emxarms:339x57fmj": 18.97,
    "oldgun:30x06": 12.09,
    "tacz:30_06": 12.09,
    "lradd:m993": 11.96,
    "oldgun:75x54": 11.08,
    "oldgun:792x57": 11.9,
    "tacz:308": 11.93,
    "tacz:68x51fury": 12.45,
    "tacz:762x54": 12.14,
    "rfp:762x54r": 13.03,
    "oldgun:303": 11.57,
    "tacz:58x42": 9.2,
    "oldgun:65x50": 10.56,
    "cib:545x39": 8.54,
    "tacz:556x45": 9.01,
    "atea:1163x39": 11.7,
    "oldgun:792x33": 9.59,
    "classicr:300blk": 9.67,
    "classicr:762x39copper": 9.8,
    "tacz:762x39": 9.46,
    "cib:9x39mm": 7.66,
    "classicr:57x28": 5.23,
    "emxarms:402x31": 5.05,
    "emxarms:402x31fmj": 5.02,
    "emxarms:402x31rip": 5.19,
    "tacz:50ae": 10.39,
    "tacz:762x25": 5.34,
    "emxarms:x16sg": 16.31,
    "tacz:357mag": 7.71,
    "emxarms:410x57ap": 7.87,
    "lradd:arrow": 6.63,
    "tacz:46x30": 5.13,
    "tacz:9mm": 4.93,
    "lradd:flintlock_bullet": 5.57,
    "tacz:45acp": 5.27,
    "tacz:12g": 11.21,
    "emxarms:x16he": 11.21,
    "lradd:nail": 3.24
}